llama_index/vector_stores/alibabacloud_mysql/__init__.py
llama_index/vector_stores/alibabacloud_mysql/base.py
llama_index_vector_stores_alibabacloud_mysql-0.1.0.dist-info/METADATA
llama_index_vector_stores_alibabacloud_mysql-0.1.0.dist-info/WHEEL
llama_index_vector_stores_alibabacloud_mysql-0.1.0.dist-info/licenses/LICENSE
llama_index_vector_stores_alibabacloud_mysql-0.1.0.dist-info/RECORD
