Metadata-Version: 2.4
Name: llama-index-vector-stores-alibabacloud-mysql
Version: 0.1.0
Summary: llama-index vector_stores alibabacloud-mysql integration
Author: Alibaba Cloud
License-Expression: MIT
License-File: LICENSE
Requires-Python: <4.0,>=3.9
Requires-Dist: aiomysql>=0.2.0
Requires-Dist: llama-index-core<0.15,>=0.13.0
Requires-Dist: pymysql>=1.0.0
Requires-Dist: sqlalchemy<3.0.0,>=1.4.0
